<resource xmlns:xsi="http://www.w3.org/2001/XMLSchema-instance" xsi:schemaLocation="http://datacite.org/schema/kernel-4 https://schema.datacite.org/meta/kernel-4.4/metadata.xsd" xmlns="http://datacite.org/schema/kernel-4"><dates><date dateType="Available">2022-09-26</date></dates><alternateIdentifiers><alternateIdentifier alternateIdentifierType="urn">urn:nbn:at:at-ubl:3-14808</alternateIdentifier></alternateIdentifiers><identifier identifierType="DOI">10.35011/IDIMT-2022-117</identifier><language>eng</language><creators><creator><creatorName nameType="Personal">&#352;t&#283;p&#225;nek, Lubomir</creatorName><givenName> Lubomir</givenName><familyName>&#352;t&#283;p&#225;nek</familyName></creator><creator><creatorName nameType="Personal">Habarta, Filip</creatorName><givenName> Filip</givenName><familyName>Habarta</familyName></creator><creator><creatorName nameType="Personal">Mal&#225;, Ivana</creatorName><givenName> Ivana</givenName><familyName>Mal&#225;</familyName></creator><creator><creatorName nameType="Personal">Marek, Lubo&#353;</creatorName><givenName> Lubo&#353;</givenName><familyName>Marek</familyName></creator></creators><titles><title>How many conference submissions should we expect in total?</title><title titleType="Subtitle">an empirical model predicting the total number of submissions</title></titles><publisher>Trauner Verlag</publisher><publicationYear>2022</publicationYear><sizes><size>8 pages</size></sizes><formats><format>PDF</format></formats><descriptions><description descriptionType="SeriesInformation">IDIMT-2022 Digitalization of society, business and management in a pandemic; 30th Interdisciplinary Information Management Talk / Chroust, Gerhard ; Doucek, Petr ; O&#353;krdal, V&#225;clav, page 117-124</description><description descriptionType="Abstract">Considering a usual format of a scientific conference, the number of total conference proceeding submissions behaves like a random variable and, thus, due to randomness, may sometimes result in an unexpected number of submissions. That could be an issue whether, mainly, the total number of submissions at the conference submission deadline is lower than expected. Although there is empirically based evidence that, e. g., the submission rate increases as the deadline approaches, numerical statistical modeling of the submissions&#8217; number in time before the deadline is generally missing. This work uses real data of conference submission times and numbers and models the number of submissions as a time-variant variable. Furthermore, we predict the total number of conference submissions using preliminary submission estimates obtained at a given time before the submission deadline. That may help the conference committee realize whether they may expect a feasible high submission number in total or must consider a submission deadline extension, considering that the entire submission number may be insufficient. Finally, we try to on-the-fly estimate the time moment before the deadline when roughly a half (a quarter, a tenth) of a total number of submissions is generally submitted to make deadline extension management possible.</description></descriptions><rightsList><rights rightsIdentifier="CC BY-NC-ND 4.0" rightsURI="https://creativecommons.org/licenses/by-nc-nd/4.0/legalcode" /></rightsList><resourceType resourceTypeGeneral="ConferencePaper" /></resource>